nswcaselaw/__init__.py
nswcaselaw/constants.py
nswcaselaw/decision.py
nswcaselaw/nswcaselaw.py
nswcaselaw/search.py
nswcaselaw-0.1.2.dist-info/LICENSE.txt
nswcaselaw-0.1.2.dist-info/METADATA
nswcaselaw-0.1.2.dist-info/WHEEL
nswcaselaw-0.1.2.dist-info/entry_points.txt
nswcaselaw-0.1.2.dist-info/top_level.txt
nswcaselaw-0.1.2.dist-info/RECORD
