Metadata-Version: 2.1
Name: nswcaselaw
Version: 0.1.2
Summary: Toolkit for working with NSW CaseLaw decisions
Home-page: https://github.com/Sydney-Informatics-Hub/nswcaselaw/
Author: Mike Lynch
Author-email: mlynch@sydney.edu.au
License: MIT
Platform: any
Classifier: Development Status :: 3 - Alpha
Classifier: Programming Language :: Python
License-File: LICENSE.txt
Requires-Dist: requests
Requires-Dist: beautifulsoup4
Requires-Dist: importlib-metadata ; python_version < "3.8"
Provides-Extra: test
Requires-Dist: pytest ; extra == 'test'
Provides-Extra: testing
Requires-Dist: setuptools ; extra == 'testing'
Requires-Dist: pytest ; extra == 'testing'
Requires-Dist: pytest-cov ; extra == 'testing'
